{"name": "2012", "children": [{"name": "Agriculture", "children": [{"diff": -0.16824544040718223, "kind": "Discretionary", "oldsize": 7.0729999999999995, "name": "Department of Agriculture", "size": 5.883}, {"diff": 0.19643713053203388, "kind": "Mandatory", "oldsize": 12.517999999999999, "name": "Department of Agriculture", "size": 14.976999999999999}]}, {"name": "Commerce and housing credit", "children": [{"diff": 0.21301775147928995, "kind": "Discretionary", "oldsize": 0.16899999999999998, "name": "Commodity Futures Trading Commission", "size": 0.20499999999999999}, {"diff": -0.292022792022792, "kind": "Discretionary", "oldsize": 0.70199999999999996, "name": "Department of Agriculture", "size": 0.497}, {"diff": -1.3494949494949495, "kind": "Mandatory", "oldsize": -0.495, "name": "Department of Agriculture", "size": 0.17299999999999999}, {"diff": -0.7015365703749231, "kind": "Discretionary", "oldsize": 8.1349999999999998, "name": "Department of Commerce", "size": 2.4279999999999999}, {"diff": -0.8589211618257261, "kind": "Mandatory", "oldsize": 0.24099999999999999, "name": "Department of Commerce", "size": 0.033999999999999996}, {"diff": 0.6865520728008089, "kind": "Discretionary", "oldsize": -3.956, "name": "Department of Housing and Urban Development", "size": -6.6719999999999997}, {"diff": 0.32074805928016936, "kind": "Mandatory", "oldsize": 2.8340000000000001, "name": "Department of Housing and Urban Development", "size": 3.7429999999999999}, {"diff": 0.8260869565217391, "kind": "Discretionary", "oldsize": 0.023, "name": "Department of the Treasury", "size": 0.041999999999999996}, {"diff": -0.9666310751379483, "kind": "Mandatory", "oldsize": -133.92699999999999, "name": "Department of the Treasury", "size": -4.4689999999999994}, {"diff": -0.3333333333333333, "kind": "Discretionary", "oldsize": -0.0060000000000000001, "name": "Federal Communications Commission", "size": -0.0040000000000000001}, {"diff": 0.12438368444643658, "kind": "Mandatory", "oldsize": 8.9239999999999995, "name": "Federal Communications Commission", "size": 10.033999999999999}, {"diff": -0.12121212121212122, "kind": "Discretionary", "oldsize": 0.033000000000000002, "name": "Federal Deposit Insurance Corporation", "size": 0.028999999999999998}, {"diff": -4.5, "kind": "Mandatory", "oldsize": -0.0060000000000000001, "name": "Federal Deposit Insurance Corporation", "size": 0.020999999999999998}, {"diff": 0.0, "kind": "Mandatory", "oldsize": 0.0030000000000000001, "name": "Federal Financial Institutions Examination Council", "size": 0.0030000000000000001}, {"diff": 0.5664335664335665, "kind": "Mandatory", "oldsize": 0.14299999999999999, "name": "Federal Housing Finance Agency", "size": 0.22399999999999998}, {"diff": 0.024390243902439025, "kind": "Discretionary", "oldsize": 0.20499999999999999, "name": "Federal Trade Commission", "size": 0.20999999999999999}, {"diff": -0.08108108108108109, "kind": "Discretionary", "oldsize": 0.036999999999999998, "name": "General Services Administration", "size": 0.033999999999999996}, {"diff": -0.23809523809523808, "kind": "Discretionary", "oldsize": 0.020999999999999998, "name": "Legislative Branch", "size": 0.016}, {"diff": -0.16666666666666666, "kind": "Mandatory", "oldsize": 0.0060000000000000001, "name": "Legislative Branch", "size": 0.0050000000000000001}, {"diff": 0.0, "kind": "Discretionary", "oldsize": 0.001, "name": "National Credit Union Administration", "size": 0.001}, {"diff": -0.11081081081081082, "kind": "Discretionary", "oldsize": 0.37, "name": "Postal Service", "size": 0.32899999999999996}, {"diff": -0.5504607777028546, "kind": "Mandatory", "oldsize": 4.4489999999999998, "name": "Postal Service", "size": 2.0}, {"diff": 0.3902439024390244, "kind": "Mandatory", "oldsize": 0.16399999999999998, "name": "Public Company Accounting Oversight Board", "size": 0.22799999999999998}, {"diff": -1.0948275862068966, "kind": "Discretionary", "oldsize": -0.34799999999999998, "name": "Securities and Exchange Commission", "size": 0.033000000000000002}, {"diff": -0.9424778761061947, "kind": "Mandatory", "oldsize": 0.45199999999999996, "name": "Securities and Exchange Commission", "size": 0.025999999999999999}, {"diff": -0.5310304449648712, "kind": "Discretionary", "oldsize": 1.708, "name": "Small Business Administration", "size": 0.80099999999999993}, {"diff": -0.6317907444668008, "kind": "Mandatory", "oldsize": 4.4729999999999999, "name": "Small Business Administration", "size": 1.647}]}, {"name": "Community and regional development", "children": [{"diff": -0.10526315789473684, "kind": "Discretionary", "oldsize": 0.075999999999999998, "name": "Appalachian Regional Commission", "size": 0.067999999999999991}, {"diff": 0.0, "kind": "Discretionary", "oldsize": 0.002, "name": "Commission of Fine Arts", "size": 0.002}, {"diff": -0.07692307692307693, "kind": "Discretionary", "oldsize": 0.012999999999999999, "name": "Delta Regional Authority", "size": 0.012}, {"diff": 0.21052631578947367, "kind": "Discretionary", "oldsize": 0.019, "name": "Denali Commission", "size": 0.023}, {"diff": -0.08742194469223907, "kind": "Discretionary", "oldsize": 1.121, "name": "Department of Agriculture", "size": 1.0229999999999999}, {"diff": -17.35, "kind": "Mandatory", "oldsize": 0.02, "name": "Department of Agriculture", "size": -0.32700000000000001}, {"diff": 0.31988472622478387, "kind": "Discretionary", "oldsize": 0.34699999999999998, "name": "Department of Commerce", "size": 0.45799999999999996}, {"diff": -0.1195580474934037, "kind": "Discretionary", "oldsize": 12.128, "name": "Department of Homeland Security", "size": 10.677999999999999}, {"diff": -0.196, "kind": "Mandatory", "oldsize": -0.5, "name": "Department of Homeland Security", "size": -0.40199999999999997}, {"diff": -0.24564902102973168, "kind": "Discretionary", "oldsize": 5.516, "name": "Department of Housing and Urban Development", "size": 4.1609999999999996}, {"diff": 1.25, "kind": "Mandatory", "oldsize": 0.0040000000000000001, "name": "Department of Housing and Urban Development", "size": 0.0089999999999999993}, {"diff": -0.0562273276904474, "kind": "Discretionary", "oldsize": 1.6539999999999999, "name": "Department of the Interior", "size": 1.5609999999999999}, {"diff": 2.652173913043478, "kind": "Mandatory", "oldsize": 0.023, "name": "Department of the Interior", "size": 0.083999999999999991}, {"diff": -0.15, "kind": "Discretionary", "oldsize": 0.26000000000000001, "name": "Department of the Treasury", "size": 0.221}, {"diff": -109.25, "kind": "Mandatory", "oldsize": -0.0040000000000000001, "name": "Department of the Treasury", "size": 0.433}, {"diff": -0.1111111111111111, "kind": "Discretionary", "oldsize": 0.0089999999999999993, "name": "National Capital Planning Commission", "size": 0.0080000000000000002}, {"diff": -0.07725321888412018, "kind": "Discretionary", "oldsize": 0.23299999999999998, "name": "Neighborhood Reinvestment Corporation", "size": 0.215}, {"diff": -0.5, "kind": "Discretionary", "oldsize": 0.002, "name": "Northern Border Regional Commission", "size": 0.001}, {"diff": 0.5, "kind": "Discretionary", "oldsize": 0.078, "name": "Small Business Administration", "size": 0.11699999999999999}, {"diff": -0.2535211267605634, "kind": "Mandatory", "oldsize": 0.21299999999999999, "name": "Small Business Administration", "size": 0.159}]}, {"name": "Education, training, employment, and social services", "children": [{"diff": -0.5, "kind": "Mandatory", "oldsize": 0.0040000000000000001, "name": "Barry Goldwater Scholarship and Excellence in Education Foundation", "size": 0.002}, {"diff": 0.0, "kind": "Discretionary", "oldsize": 0.001, "name": "Christopher Columbus Fellowship Foundation", "size": 0.001}, {"diff": -0.8, "kind": "Discretionary", "oldsize": 0.01, "name": "Commission of Fine Arts", "size": 0.002}, {"diff": 0.0, "kind": "Discretionary", "oldsize": 0.0050000000000000001, "name": "Committee for Purchase from People Who Are Blind or Severely Disabled", "size": 0.0050000000000000001}, {"diff": -0.08782608695652173, "kind": "Discretionary", "oldsize": 1.1499999999999999, "name": "Corporation for National and Community Service", "size": 1.0489999999999999}, {"diff": -0.7333333333333333, "kind": "Mandatory", "oldsize": 0.014999999999999999, "name": "Corporation for National and Community Service", "size": 0.0040000000000000001}, {"diff": -0.1225296442687747, "kind": "Discretionary", "oldsize": 0.50600000000000001, "name": "Corporation for Public Broadcasting", "size": 0.44400000000000001}, {"diff": -1.25, "kind": "Discretionary", "oldsize": 0.02, "name": "Department of Commerce", "size": -0.0050000000000000001}, {"diff": 0.05086838937610405, "kind": "Discretionary", "oldsize": 63.968999999999994, "name": "Department of Education", "size": 67.222999999999999}, {"diff": 8.504281636536632, "kind": "Mandatory", "oldsize": -1.0509999999999999, "name": "Department of Education", "size": -9.988999999999999}, {"diff": 0.050505050505050504, "kind": "Discretionary", "oldsize": 10.889999999999999, "name": "Department of Health and Human Services", "size": 11.44}, {"diff": 0.0013043478260869566, "kind": "Mandatory", "oldsize": 2.2999999999999998, "name": "Department of Health and Human Services", "size": 2.3029999999999999}, {"diff": -0.13708574434508153, "kind": "Discretionary", "oldsize": 9.504999999999999, "name": "Department of Labor", "size": 8.202}, {"diff": 1.712979890310786, "kind": "Mandatory", "oldsize": 0.54699999999999993, "name": "Department of Labor", "size": 1.484}, {"diff": -0.0149812734082397, "kind": "Discretionary", "oldsize": 0.80099999999999993, "name": "Department of the Interior", "size": 0.78899999999999992}, {"diff": 0.6159439106725526, "kind": "Mandatory", "oldsize": 3.851, "name": "Department of the Treasury", "size": 6.2229999999999999}, {"diff": -0.18181818181818182, "kind": "Discretionary", "oldsize": 0.11, "name": "District of Columbia", "size": 0.089999999999999997}, {"diff": -0.02127659574468085, "kind": "Discretionary", "oldsize": 0.047, "name": "Federal Mediation and Conciliation Service", "size": 0.045999999999999999}, {"diff": 0.0, "kind": "Discretionary", "oldsize": 0.001, "name": "Harry S Truman Scholarship Foundation", "size": 0.001}, {"diff": 0.0, "kind": "Mandatory", "oldsize": 0.001, "name": "Harry S Truman Scholarship Foundation", "size": 0.001}, {"diff": 0.125, "kind": "Discretionary", "oldsize": 0.0080000000000000002, "name": "Institute of American Indian and Alaska Native Culture and Arts Development", "size": 0.0089999999999999993}, {"diff": -0.17375886524822695, "kind": "Discretionary", "oldsize": 0.28199999999999997, "name": "Institute of Museum and Library Services", "size": 0.23299999999999998}, {"diff": -0.08644400785854617, "kind": "Discretionary", "oldsize": 0.50900000000000001, "name": "Legislative Branch", "size": 0.46499999999999997}, {"diff": -0.5, "kind": "Mandatory", "oldsize": 0.0040000000000000001, "name": "Legislative Branch", "size": 0.002}, {"diff": -0.3333333333333333, "kind": "Discretionary", "oldsize": 0.0030000000000000001, "name": "Morris K. Udall and Stewart L. Udall Foundation", "size": 0.002}, {"diff": 0.0, "kind": "Discretionary", "oldsize": 0.0030000000000000001, "name": "National Council on Disability", "size": 0.0030000000000000001}, {"diff": -0.13095238095238096, "kind": "Discretionary", "oldsize": 0.16799999999999998, "name": "National Endowment for the Arts", "size": 0.14599999999999999}, {"diff": -0.13095238095238096, "kind": "Discretionary", "oldsize": 0.16799999999999998, "name": "National Endowment for the Humanities", "size": 0.14599999999999999}, {"diff": -0.0176678445229682, "kind": "Discretionary", "oldsize": 0.28299999999999997, "name": "National Labor Relations Board", "size": 0.27799999999999997}, {"diff": 0.0, "kind": "Discretionary", "oldsize": 0.012999999999999999, "name": "National Mediation Board", "size": 0.012999999999999999}, {"diff": 0.007142857142857143, "kind": "Discretionary", "oldsize": 0.97999999999999998, "name": "Smithsonian Institution", "size": 0.98699999999999999}, {"diff": 0.04081632653061224, "kind": "Discretionary", "oldsize": 0.048999999999999995, "name": "United States Holocaust Memorial Museum", "size": 0.050999999999999997}]}, {"name": "Energy", "children": [{"diff": 1.0, "kind": "Discretionary", "oldsize": -0.020999999999999998, "name": "Department of Agriculture", "size": -0.041999999999999996}, {"diff": -0.8775933609958506, "kind": "Mandatory", "oldsize": -0.48199999999999998, "name": "Department of Agriculture", "size": -0.058999999999999997}, {"diff": 0.29909706546275394, "kind": "Discretionary", "oldsize": 3.544, "name": "Department of Energy", "size": 4.6040000000000001}, {"diff": 2.5517857142857143, "kind": "Mandatory", "oldsize": -0.55999999999999994, "name": "Department of Energy", "size": -1.9889999999999999}, {"diff": 0.2641157256182921, "kind": "Mandatory", "oldsize": 4.2859999999999996, "name": "Department of the Treasury", "size": 5.4180000000000001}, {"diff": 0.02877697841726619, "kind": "Discretionary", "oldsize": 0.13899999999999998, "name": "Nuclear Regulatory Commission", "size": 0.14299999999999999}, {"diff": -0.25, "kind": "Discretionary", "oldsize": 0.0040000000000000001, "name": "Nuclear Waste Technical Review Board", "size": 0.0030000000000000001}, {"diff": -0.75, "kind": "Discretionary", "oldsize": 0.0040000000000000001, "name": "Office of the Federal Coordinator for Alaska Natural Gas Transportation Projects", "size": 0.001}]}, {"name": "General Govt", "children": [{"diff": -0.3060836501901141, "kind": "Mandatory", "oldsize": 0.52600000000000002, "name": "Department of Agriculture", "size": 0.36499999999999999}, {"diff": 0.25882352941176473, "kind": "Mandatory", "oldsize": 0.084999999999999992, "name": "Department of Homeland Security", "size": 0.107}, {"diff": -0.09126984126984126, "kind": "Discretionary", "oldsize": 0.252, "name": "Department of the Interior", "size": 0.22899999999999998}, {"diff": 0.19486798066195612, "kind": "Mandatory", "oldsize": 2.6890000000000001, "name": "Department of the Interior", "size": 3.2129999999999996}, {"diff": -0.0215548558973117, "kind": "Discretionary", "oldsize": 12.386999999999999, "name": "Department of the Treasury", "size": 12.119999999999999}, {"diff": 1.5533917559234014, "kind": "Mandatory", "oldsize": 3.081, "name": "Department of the Treasury", "size": 7.867}, {"diff": -0.1683673469387755, "kind": "Discretionary", "oldsize": 0.39199999999999996, "name": "District of Columbia", "size": 0.32600000000000001}, {"diff": -0.898876404494382, "kind": "Discretionary", "oldsize": 0.088999999999999996, "name": "Election Assistance Commission", "size": 0.0089999999999999993}, {"diff": -0.11085450346420324, "kind": "Discretionary", "oldsize": 0.433, "name": "Executive Office of the President", "size": 0.38500000000000001}, {"diff": -0.3464052287581699, "kind": "Discretionary", "oldsize": 0.153, "name": "Federal Drug Control Programs", "size": 0.099999999999999992}, {"diff": -0.014925373134328358, "kind": "Discretionary", "oldsize": 0.06699999999999999, "name": "Federal Election Commission", "size": 0.066000000000000003}, {"diff": 0.0, "kind": "Discretionary", "oldsize": 0.024999999999999998, "name": "Federal Labor Relations Authority", "size": 0.024999999999999998}, {"diff": -4.504166666666666, "kind": "Discretionary", "oldsize": 0.23999999999999999, "name": "General Services Administration", "size": -0.84099999999999997}, {"diff": -1.75, "kind": "Mandatory", "oldsize": 0.0040000000000000001, "name": "General Services Administration", "size": -0.0030000000000000001}, {"diff": -0.07103298820130026, "kind": "Discretionary", "oldsize": 4.1529999999999996, "name": "Legislative Branch", "size": 3.8579999999999997}, {"diff": -0.050724637681159424, "kind": "Mandatory", "oldsize": 0.13799999999999998, "name": "Legislative Branch", "size": 0.13100000000000001}, {"diff": 0.0, "kind": "Discretionary", "oldsize": 0.040000000000000001, "name": "Merit Systems Protection Board", "size": 0.040000000000000001}, {"diff": -0.17903930131004367, "kind": "Discretionary", "oldsize": 0.45799999999999996, "name": "National Archives and Records Administration", "size": 0.376}, {"diff": 0.0, "kind": "Discretionary", "oldsize": 0.013999999999999999, "name": "Office of Government Ethics", "size": 0.013999999999999999}, {"diff": 0.0, "kind": "Discretionary", "oldsize": 0.0080000000000000002, "name": "Office of Navajo and Hopi Indian Relocation", "size": 0.0080000000000000002}, {"diff": -0.04716981132075472, "kind": "Discretionary", "oldsize": 0.106, "name": "Office of Personnel Management", "size": 0.10099999999999999}, {"diff": 0.05555555555555555, "kind": "Discretionary", "oldsize": 0.017999999999999999, "name": "Office of Special Counsel", "size": 0.019}, {"diff": 0.0, "kind": "Discretionary", "oldsize": 0.001, "name": "Other Commissions and Boards", "size": 0.001}, {"diff": 0.5, "kind": "Discretionary", "oldsize": 0.002, "name": "United States Interagency Council on Homelessness", "size": 0.0030000000000000001}]}, {"name": "Health", "children": [{"diff": -0.025423728813559324, "kind": "Discretionary", "oldsize": 0.11799999999999999, "name": "Consumer Product Safety Commission", "size": 0.11499999999999999}, {"diff": -0.014720314033366046, "kind": "Discretionary", "oldsize": 1.0189999999999999, "name": "Department of Agriculture", "size": 1.004}, {"diff": -0.0814151747655584, "kind": "Discretionary", "oldsize": 65.688000000000002, "name": "Department of Health and Human Services", "size": 60.339999999999996}, {"diff": -0.010406716084202504, "kind": "Mandatory", "oldsize": 771.52099999999996, "name": "Department of Health and Human Services", "size": 763.49199999999996}, {"diff": 0.015167930660888408, "kind": "Discretionary", "oldsize": 0.92299999999999993, "name": "Department of Labor", "size": 0.93699999999999994}, {"diff": 0.4682080924855491, "kind": "Mandatory", "oldsize": 0.17299999999999999, "name": "Department of the Interior", "size": 0.254}, {"diff": 0.2857142857142857, "kind": "Discretionary", "oldsize": 0.013999999999999999, "name": "Federal Mine Safety and Health Review Commission", "size": 0.017999999999999999}, {"diff": -0.3333333333333333, "kind": "Discretionary", "oldsize": 0.0089999999999999993, "name": "Legislative Branch", "size": 0.0060000000000000001}, {"diff": 0.0, "kind": "Discretionary", "oldsize": 0.012, "name": "Occupational Safety and Health Review Commission", "size": 0.012}, {"diff": 0.0, "kind": "Discretionary", "oldsize": 0.033000000000000002, "name": "Office of Personnel Management", "size": 0.033000000000000002}, {"diff": 0.10833593506088042, "kind": "Mandatory", "oldsize": 9.609, "name": "Office of Personnel Management", "size": 10.65}, {"diff": 0.013104487997216746, "kind": "Mandatory", "oldsize": 8.6229999999999993, "name": "Other Defense Civil Programs", "size": 8.7359999999999989}]}, {"name": "Income Security", "children": [{"diff": -0.10188154800085525, "kind": "Discretionary", "oldsize": 9.3539999999999992, "name": "Department of Agriculture", "size": 8.4009999999999998}, {"diff": 0.23730742699471144, "kind": "Mandatory", "oldsize": 86.97999999999999, "name": "Department of Agriculture", "size": 107.621}, {"diff": -0.18084705290938796, "kind": "Discretionary", "oldsize": 7.9569999999999999, "name": "Department of Health and Human Services", "size": 6.5179999999999998}, {"diff": -0.027410419802107015, "kind": "Mandatory", "oldsize": 31.228999999999999, "name": "Department of Health and Human Services", "size": 30.372999999999998}, {"diff": -0.4, "kind": "Discretionary", "oldsize": 0.19999999999999998, "name": "Department of Homeland Security", "size": 0.12}, {"diff": -0.057262298269492515, "kind": "Discretionary", "oldsize": 41.143999999999998, "name": "Department of Housing and Urban Development", "size": 38.787999999999997}, {"diff": 0.3156697009102731, "kind": "Discretionary", "oldsize": 3.0760000000000001, "name": "Department of Labor", "size": 4.0469999999999997}, {"diff": -0.4475056163313147, "kind": "Mandatory", "oldsize": 163.80799999999999, "name": "Department of Labor", "size": 90.503}, {"diff": -0.2485835489673615, "kind": "Mandatory", "oldsize": 103.95699999999999, "name": "Department of the Treasury", "size": 78.114999999999995}, {"diff": 0.0, "kind": "Discretionary", "oldsize": 0.104, "name": "Office of Personnel Management", "size": 0.104}, {"diff": 0.06913548312927516, "kind": "Mandatory", "oldsize": 69.587999999999994, "name": "Office of Personnel Management", "size": 74.399000000000001}, {"diff": -0.3880597014925373, "kind": "Discretionary", "oldsize": 0.13399999999999998, "name": "Other Defense Civil Programs", "size": 0.08199999999999999}, {"diff": 0.027346043925928827, "kind": "Mandatory", "oldsize": 51.085999999999999, "name": "Other Defense Civil Programs", "size": 52.482999999999997}, {"diff": -0.09944751381215469, "kind": "Discretionary", "oldsize": 0.18099999999999999, "name": "Railroad Retirement Board", "size": 0.16300000000000001}, {"diff": 0.006701631701631702, "kind": "Mandatory", "oldsize": 6.8639999999999999, "name": "Railroad Retirement Board", "size": 6.9099999999999993}, {"diff": 0.0339943342776204, "kind": "Discretionary", "oldsize": 3.5299999999999998, "name": "Social Security Administration", "size": 3.6499999999999999}, {"diff": 0.02288575413246759, "kind": "Mandatory", "oldsize": 43.738999999999997, "name": "Social Security Administration", "size": 44.739999999999995}]}, {"name": "Intl Affairs", "children": [{"diff": 0.0026666666666666666, "kind": "Discretionary", "oldsize": 0.75, "name": "Broadcasting Board of Governors", "size": 0.752}, {"diff": -0.1951219512195122, "kind": "Discretionary", "oldsize": 2.0499999999999998, "name": "Department of Agriculture", "size": 1.6499999999999999}, {"diff": -0.30563002680965146, "kind": "Mandatory", "oldsize": -0.373, "name": "Department of Agriculture", "size": -0.25900000000000001}, {"diff": 0.0, "kind": "Discretionary", "oldsize": 0.002, "name": "Department of Justice", "size": 0.002}, {"diff": -0.009477862177513173, "kind": "Discretionary", "oldsize": 29.225999999999999, "name": "Department of State", "size": 28.948999999999998}, {"diff": -0.5492957746478874, "kind": "Mandatory", "oldsize": 0.070999999999999994, "name": "Department of State", "size": 0.032000000000000001}, {"diff": 1.0, "kind": "Mandatory", "oldsize": -0.001, "name": "Department of Transportation", "size": -0.002}, {"diff": -401.0, "kind": "Discretionary", "oldsize": 0.0030000000000000001, "name": "Export-Import Bank of the United States", "size": -1.2}, {"diff": -0.872168284789644, "kind": "Mandatory", "oldsize": 0.61799999999999999, "name": "Export-Import Bank of the United States", "size": 0.079000000000000001}, {"diff": -0.03198680292910598, "kind": "Discretionary", "oldsize": 24.853999999999999, "name": "International Assistance Programs", "size": 24.058999999999997}, {"diff": 11.041218086742541, "kind": "Mandatory", "oldsize": 3.2509999999999999, "name": "International Assistance Programs", "size": 39.146000000000001}, {"diff": -0.012345679012345678, "kind": "Discretionary", "oldsize": 0.081000000000000003, "name": "International Trade Commission", "size": 0.080000000000000002}, {"diff": 0.0, "kind": "Mandatory", "oldsize": 0.002, "name": "Japan-United States Friendship Commission", "size": 0.002}, {"diff": -0.23076923076923078, "kind": "Discretionary", "oldsize": 0.012999999999999999, "name": "Legislative Branch", "size": 0.01}, {"diff": -0.20408163265306123, "kind": "Discretionary", "oldsize": 0.048999999999999995, "name": "United States Institute of Peace", "size": 0.039}]}, {"name": "Justice", "children": [{"diff": 0.0, "kind": "Discretionary", "oldsize": 0.0069999999999999993, "name": "Access Board", "size": 0.0069999999999999993}, {"diff": 0.5, "kind": "Discretionary", "oldsize": 0.002, "name": "Administrative Conference of the United States", "size": 0.0030000000000000001}, {"diff": 0.0, "kind": "Discretionary", "oldsize": 0.0089999999999999993, "name": "Commission on Civil Rights", "size": 0.0089999999999999993}, {"diff": 0.0047169811320754715, "kind": "Discretionary", "oldsize": 0.21199999999999999, "name": "Court Services and Offender Supervision Agency for the District of Columbia", "size": 0.21299999999999999}, {"diff": 0.0, "kind": "Discretionary", "oldsize": 0.16300000000000001, "name": "Department of Education", "size": 0.16300000000000001}, {"diff": 0.07894736842105263, "kind": "Discretionary", "oldsize": 0.037999999999999999, "name": "Department of Health and Human Services", "size": 0.040999999999999995}, {"diff": -0.011927272727272727, "kind": "Discretionary", "oldsize": 20.625, "name": "Department of Homeland Security", "size": 20.378999999999998}, {"diff": 0.6954624781849913, "kind": "Mandatory", "oldsize": -1.1459999999999999, "name": "Department of Homeland Security", "size": -1.9429999999999998}, {"diff": -0.013793103448275862, "kind": "Discretionary", "oldsize": 0.14499999999999999, "name": "Department of Housing and Urban Development", "size": 0.14299999999999999}, {"diff": -0.05584426648492077, "kind": "Discretionary", "oldsize": 23.475999999999999, "name": "Department of Justice", "size": 22.164999999999999}, {"diff": 1.0359212050984936, "kind": "Mandatory", "oldsize": 2.589, "name": "Department of Justice", "size": 5.2709999999999999}, {"diff": -0.005256241787122208, "kind": "Discretionary", "oldsize": 0.76100000000000001, "name": "Department of the Treasury", "size": 0.75700000000000001}, {"diff": -1.0167753960857409, "kind": "Mandatory", "oldsize": 1.073, "name": "Department of the Treasury", "size": -0.017999999999999999}, {"diff": -0.01907356948228883, "kind": "Discretionary", "oldsize": 0.36699999999999999, "name": "Equal Employment Opportunity Commission", "size": 0.35999999999999999}, {"diff": -0.036036036036036036, "kind": "Discretionary", "oldsize": 0.222, "name": "Federal Drug Control Programs", "size": 0.214}, {"diff": 0.014137020351095231, "kind": "Discretionary", "oldsize": 6.4369999999999994, "name": "Judicial Branch", "size": 6.5279999999999996}, {"diff": -0.10692771084337349, "kind": "Mandatory", "oldsize": 0.66399999999999992, "name": "Judicial Branch", "size": 0.59299999999999997}, {"diff": -0.17142857142857143, "kind": "Discretionary", "oldsize": 0.41999999999999998, "name": "Legal Services Corporation", "size": 0.34799999999999998}, {"diff": 0.061224489795918366, "kind": "Discretionary", "oldsize": 0.048999999999999995, "name": "Legislative Branch", "size": 0.051999999999999998}, {"diff": 0.0, "kind": "Discretionary", "oldsize": 0.036999999999999998, "name": "Public Defender Service for the District of Columbia", "size": 0.036999999999999998}, {"diff": 0.0, "kind": "Discretionary", "oldsize": 0.0050000000000000001, "name": "State Justice Institute", "size": 0.0050000000000000001}]}, {"name": "National Defense", "children": [{"diff": 0.7663230240549829, "kind": "Mandatory", "oldsize": 0.29099999999999998, "name": "Central Intelligence Agency", "size": 0.51400000000000001}, {"diff": -0.1865671641791045, "kind": "Discretionary", "oldsize": 0.13399999999999998, "name": "Corps of Engineers--Civil Works", "size": 0.109}, {"diff": 0.11538461538461539, "kind": "Discretionary", "oldsize": 0.025999999999999999, "name": "Defense Nuclear Facilities Safety Board", "size": 0.028999999999999998}, {"diff": 0.1724137931034483, "kind": "Discretionary", "oldsize": 0.028999999999999998, "name": "Department of Commerce", "size": 0.033999999999999996}, {"diff": -0.06512819547293217, "kind": "Discretionary", "oldsize": 690.46899999999994, "name": "Department of Defense--Military Programs", "size": 645.5}, {"diff": 0.9117249372223295, "kind": "Mandatory", "oldsize": 5.1769999999999996, "name": "Department of Defense--Military Programs", "size": 9.8970000000000002}, {"diff": 0.021438114903437385, "kind": "Discretionary", "oldsize": 16.465999999999998, "name": "Department of Energy", "size": 16.818999999999999}, {"diff": 0.007817589576547232, "kind": "Discretionary", "oldsize": 1.5349999999999999, "name": "Department of Homeland Security", "size": 1.5469999999999999}, {"diff": 0.07000903342366757, "kind": "Discretionary", "oldsize": 4.4279999999999999, "name": "Department of Justice", "size": 4.7379999999999995}, {"diff": 0.25, "kind": "Mandatory", "oldsize": 0.059999999999999998, "name": "Department of Justice", "size": 0.074999999999999997}, {"diff": 0.0, "kind": "Discretionary", "oldsize": 0.17399999999999999, "name": "Department of Transportation", "size": 0.17399999999999999}, {"diff": -0.22411347517730495, "kind": "Discretionary", "oldsize": 0.70499999999999996, "name": "Intelligence Community Management Account", "size": 0.54699999999999993}, {"diff": 0.0, "kind": "Discretionary", "oldsize": 0.067999999999999991, "name": "National Science Foundation", "size": 0.067999999999999991}, {"diff": 0.0, "kind": "Discretionary", "oldsize": 0.024, "name": "Other Defense Civil Programs", "size": 0.024}]}, {"name": "Natural Resources, Environment", "children": [{"diff": 0.0, "kind": "Discretionary", "oldsize": 0.0060000000000000001, "name": "Advisory Council on Historic Preservation", "size": 0.0060000000000000001}, {"diff": 0.0, "kind": "Discretionary", "oldsize": 0.010999999999999999, "name": "Chemical Safety and Hazard Investigation Board", "size": 0.010999999999999999}, {"diff": 0.19625334522747548, "kind": "Discretionary", "oldsize": 5.6049999999999995, "name": "Corps of Engineers--Civil Works", "size": 6.7050000000000001}, {"diff": -0.023255813953488372, "kind": "Mandatory", "oldsize": 0.042999999999999997, "name": "Corps of Engineers--Civil Works", "size": 0.041999999999999996}, {"diff": -0.10293653299652668, "kind": "Discretionary", "oldsize": 6.3339999999999996, "name": "Department of Agriculture", "size": 5.6819999999999995}, {"diff": 0.11177730192719486, "kind": "Mandatory", "oldsize": 4.6699999999999999, "name": "Department of Agriculture", "size": 5.1920000000000002}, {"diff": 0.02788027880278803, "kind": "Discretionary", "oldsize": 4.8780000000000001, "name": "Department of Commerce", "size": 5.0139999999999993}, {"diff": 0.27906976744186046, "kind": "Mandatory", "oldsize": 0.042999999999999997, "name": "Department of Commerce", "size": 0.055}, {"diff": 0.017241379310344827, "kind": "Discretionary", "oldsize": 0.057999999999999996, "name": "Department of Homeland Security", "size": 0.058999999999999997}, {"diff": -0.1981981981981982, "kind": "Mandatory", "oldsize": 0.222, "name": "Department of Homeland Security", "size": 0.17799999999999999}, {"diff": -0.13286713286713286, "kind": "Discretionary", "oldsize": 0.14299999999999999, "name": "Department of State", "size": 0.124}, {"diff": -0.07470108983176384, "kind": "Discretionary", "oldsize": 9.4509999999999987, "name": "Department of the Interior", "size": 8.7449999999999992}, {"diff": 0.6154608523290387, "kind": "Mandatory", "oldsize": -2.0179999999999998, "name": "Department of the Interior", "size": -3.2599999999999998}, {"diff": -0.1761723700887199, "kind": "Discretionary", "oldsize": 10.257, "name": "Environmental Protection Agency", "size": 8.4499999999999993}, {"diff": -0.2777777777777778, "kind": "Mandatory", "oldsize": -0.089999999999999997, "name": "Environmental Protection Agency", "size": -0.065000000000000002}, {"diff": 0.0, "kind": "Discretionary", "oldsize": 0.0030000000000000001, "name": "Marine Mammal Commission", "size": 0.0030000000000000001}, {"diff": 0.0, "kind": "Discretionary", "oldsize": 0.0040000000000000001, "name": "Morris K. Udall and Stewart L. Udall Foundation", "size": 0.0040000000000000001}, {"diff": -0.4782608695652174, "kind": "Discretionary", "oldsize": 0.023, "name": "Presidio Trust", "size": 0.012}]}, {"name": "Net interest", "children": []}, {"name": "S&T--Space", "children": [{"diff": -0.0060435132957292505, "kind": "Discretionary", "oldsize": 4.9639999999999995, "name": "Department of Energy", "size": 4.9340000000000002}, {"diff": -0.056396752249286815, "kind": "Discretionary", "oldsize": 18.227999999999998, "name": "National Aeronautics and Space Administration", "size": 17.199999999999999}, {"diff": 0.023365172667156504, "kind": "Discretionary", "oldsize": 6.8049999999999997, "name": "National Science Foundation", "size": 6.9639999999999995}, {"diff": 0.4175824175824176, "kind": "Mandatory", "oldsize": 0.090999999999999998, "name": "National Science Foundation", "size": 0.129}]}, {"name": "Social Security", "children": [{"diff": 0.008848022206800832, "kind": "Discretionary", "oldsize": 5.7639999999999993, "name": "Social Security Administration", "size": 5.8149999999999995}, {"diff": 0.10088080277862965, "kind": "Mandatory", "oldsize": 701.06499999999994, "name": "Social Security Administration", "size": 771.78899999999999}]}, {"name": "Transportation", "children": [{"diff": -0.0024694944799535153, "kind": "Discretionary", "oldsize": 13.767999999999999, "name": "Department of Homeland Security", "size": 13.734}, {"diff": 0.037138927097661624, "kind": "Mandatory", "oldsize": 1.454, "name": "Department of Homeland Security", "size": 1.508}, {"diff": -0.1074364896073903, "kind": "Discretionary", "oldsize": 21.649999999999999, "name": "Department of Transportation", "size": 19.323999999999998}, {"diff": -0.19084676968312053, "kind": "Mandatory", "oldsize": 62.579000000000001, "name": "Department of Transportation", "size": 50.635999999999996}, {"diff": 0.0, "kind": "Discretionary", "oldsize": 0.024, "name": "Federal Maritime Commission", "size": 0.024}, {"diff": 0.1448692152917505, "kind": "Discretionary", "oldsize": 0.497, "name": "National Aeronautics and Space Administration", "size": 0.56899999999999995}, {"diff": 0.10526315789473684, "kind": "Discretionary", "oldsize": 0.019, "name": "National Railroad Passenger Corporation Office of Inspector General", "size": 0.020999999999999998}, {"diff": 0.04081632653061224, "kind": "Discretionary", "oldsize": 0.09799999999999999, "name": "National Transportation Safety Board", "size": 0.10199999999999999}]}, {"name": "Veterans Benefits", "children": [{"diff": 0.15217391304347827, "kind": "Discretionary", "oldsize": 0.045999999999999999, "name": "Department of Labor", "size": 0.052999999999999999}, {"diff": 0.10512830174460229, "kind": "Discretionary", "oldsize": 53.077999999999996, "name": "Department of Veterans Affairs", "size": 58.657999999999994}, {"diff": -0.08114973824928773, "kind": "Mandatory", "oldsize": 71.250999999999991, "name": "Department of Veterans Affairs", "size": 65.468999999999994}, {"diff": 0.0, "kind": "Discretionary", "oldsize": 0.123, "name": "Other Defense Civil Programs", "size": 0.123}, {"diff": -3.033333333333333, "kind": "Mandatory", "oldsize": -0.089999999999999997, "name": "Other Defense Civil Programs", "size": 0.183}, {"diff": -0.25, "kind": "Mandatory", "oldsize": 0.0080000000000000002, "name": "Social Security Administration", "size": 0.0060000000000000001}, {"diff": 0.14814814814814814, "kind": "Discretionary", "oldsize": 0.027, "name": "United States Court of Appeals for Veterans Claims", "size": 0.031}, {"diff": 0.0, "kind": "Mandatory", "oldsize": 0.001, "name": "United States Court of Appeals for Veterans Claims", "size": 0.001}]}]}